{
  "hideHud": true,
  "keyMappings": "# Insert your preferred key mappings here.\nmap h goBack\nmap l goForward\nmap H previousTab\nmap L nextTab",
  "settingsVersion": "2.1.2",
  "userDefinedLinkHintCss": "div > .vimiumHintMarker {\n/* linkhint boxes */\nbackground: #336699;\nborder: none;\n}\n\ndiv > .vimiumHintMarker span {\n/* linkhint text */\ncolor: white;\nfont-size: 12px;\n}\n\ndiv > .vimiumHintMarker > .matchingCharacter {\n}",
  "exclusionRules": [
    {
      "passKeys": "",
      "pattern": "https?://mail.google.com/*"
    },
    {
      "passKeys": "",
      "pattern": "https?://www.e-typing.ne.jp/*"
    },
    {
      "passKeys": "",
      "pattern": "https?://sushida.net/*"
    }
  ]
}
